Metadata-Version: 1.0
Name: ammu-distributions
Version: 0.1
Summary: Gaussian and Binomial distributions
Home-page: UNKNOWN
Author: Aman Bahuguna
Author-email: amanbahuguna002@gmail.com
License: UNKNOWN
Platform: UNKNOWN
